sgpaynow/__init__.py
sgpaynow/core.py
sgpaynow/dynamic.py
sgpaynow/static.py
sgpaynowqr-0.2.0.dist-info/METADATA
sgpaynowqr-0.2.0.dist-info/WHEEL
sgpaynowqr-0.2.0.dist-info/top_level.txt
sgpaynowqr-0.2.0.dist-info/RECORD
