Metadata-Version: 2.4
Name: sgpaynowqr
Version: 0.2.0
Summary: A simple library to generate Singapore PayNow QR codes.
Author: DangerousPotential
Author-email: admin@aicomputing.sg
Requires-Python: >=3.6
Requires-Dist: qrcode
Requires-Dist: pillow
Dynamic: author
Dynamic: author-email
Dynamic: requires-dist
Dynamic: requires-python
Dynamic: summary
